tplus/__init__.py
tplus/client.py
tplus/constants.py
tplus/logger.py
tplus/py.typed
tplus/version.py
tplus/client/__init__.py
tplus/client/base.py
tplus/client/orderbook.py
tplus/client/clearingengine/__init__.py
tplus/client/clearingengine/admin.py
tplus/client/clearingengine/assetregistry.py
tplus/client/clearingengine/base.py
tplus/client/clearingengine/decimal.py
tplus/client/clearingengine/deposit.py
tplus/client/clearingengine/settlement.py
tplus/client/clearingengine/vault.py
tplus/client/clearingengine/withdrawal.py
tplus/evm/__init__.py
tplus/evm/abi.py
tplus/evm/contracts.py
tplus/evm/eip712.py
tplus/evm/exceptions.py
tplus/evm/utils.py
tplus/model/__init__.py
tplus/model/asset_identifier.py
tplus/model/cancel_order.py
tplus/model/klines.py
tplus/model/limit_order.py
tplus/model/market.py
tplus/model/market_order.py
tplus/model/order.py
tplus/model/order_trigger.py
tplus/model/orderbook.py
tplus/model/replace_order.py
tplus/model/settlement.py
tplus/model/signed_message.py
tplus/model/trades.py
tplus/model/types.py
tplus/model/withdrawal.py
tplus/utils/__init__.py
tplus/utils/bytes32.py
tplus/utils/decimals.py
tplus/utils/hex.py
tplus/utils/limit_order.py
tplus/utils/market_order.py
tplus/utils/replace_order.py
tplus/utils/serializers.py
tplus/utils/signing.py
tplus/utils/user.py
tplus/utils/user/__init__.py
tplus/utils/user/ed_keyfile.py
tplus/utils/user/manager.py
tplus/utils/user/model.py
tplus/utils/user/validate.py
tpluspy-0.1.0a0.dist-info/METADATA
tpluspy-0.1.0a0.dist-info/WHEEL
tpluspy-0.1.0a0.dist-info/top_level.txt
tpluspy-0.1.0a0.dist-info/RECORD
