Metadata-Version: 2.1
Name: tpluspy
Version: 0.1.0a0
Summary: tpluspy: Client utilities for interacting with tplus
Home-page: https://github.com/tpluslabs/tpluspy
Author: TPlus Labs
Author-email: admin@tlus.cx
License: Apache-2.0
Keywords: ethereum
Classifier: Development Status :: 5 - Production/Stable
Classifier: Intended Audience :: Developers
Classifier: License :: OSI Approved :: Apache Software License
Classifier: Natural Language :: English
Classifier: Operating System :: MacOS
Classifier: Operating System :: POSIX
Classifier: Programming Language :: Python :: 3
Classifier: Programming Language :: Python :: 3.10
Classifier: Programming Language :: Python :: 3.11
Classifier: Programming Language :: Python :: 3.12
Classifier: Programming Language :: Python :: 3.13
Requires-Python: >=3.10,<4
Requires-Dist: cryptography>=44.0.1
Requires-Dist: ecdsa>=0.17
Requires-Dist: httpx>=0.20
Requires-Dist: pycryptodome>=3.17.1
Requires-Dist: pydantic<3,>=2.10.4
Requires-Dist: websockets<14,>=13.1
Requires-Dist: eth-pydantic-types<0.3,>=0.2.2
Provides-Extra: test
Requires-Dist: pytest>=6.0; extra == "test"
Requires-Dist: pytest-timeout<3,>=2.2.0; extra == "test"
Requires-Dist: pytest-mock; extra == "test"
Provides-Extra: lint
Requires-Dist: mypy<2,>=1.15.0; extra == "lint"
Requires-Dist: ruff>=0.11.7; extra == "lint"
Requires-Dist: mypy<2,>=1.15.0; extra == "lint"
Provides-Extra: release
Requires-Dist: setuptools>=75.6.0; extra == "release"
Requires-Dist: wheel; extra == "release"
Requires-Dist: twine; extra == "release"
Provides-Extra: evm
Requires-Dist: ape-tokens; extra == "evm"
Requires-Dist: click; extra == "evm"
Requires-Dist: eip712; extra == "evm"
Requires-Dist: eth-ape<0.9,>=0.8.32; extra == "evm"
